<subsystem_definition>

    <buffers>
        <in alias="st"      type="velma_core_cs_task_cs_msgs::Status"     side="bottom"   ipc="true" />
        <out alias="cmd"    type="velma_core_cs_task_cs_msgs::Command"    side="bottom"   ipc="true" />
    </buffers>

    <trigger>
        <period p="0.01" />
    </trigger>

    <errors>
    </errors>

    <predicates>
    </predicates>

    <output_scopes>
        <scope name="all" />
    </output_scopes>

    <behaviors>
        <behavior name="normal" is_initial="true"
            init_cond="FALSE"
            stop_cond="FALSE"
            err_cond="FALSE" >
            <scope name="all" />
        </behavior>
    </behaviors>

    <activity period="0.01" />

    <simulation use_ros_sim_clock="true" use_sim_clock="true" />

</subsystem_definition>
